easydrop/__init__.py
easydrop/__main__.py
easydrop/bins/.gitkeep
easydrop/bins/owl
easydrop/cli.py
easydrop/owl.py
easydrop-0.0.1a2.dist-info/LICENSE
easydrop-0.0.1a2.dist-info/WHEEL
easydrop-0.0.1a2.dist-info/METADATA
easydrop-0.0.1a2.dist-info/RECORD
