Metadata-Version: 2.1
Name: easydrop
Version: 0.0.1a2
Summary: Tool that makes using AirDrop on Linux *easy*
Home-page: https://github.com/TheLastGimbus/easydrop
License: Apache-2.0
Keywords: airdrop,sharing,nearby,wifi,awdl
Author: TheLastGimbus
Author-email: mateusz.soszynski@tuta.io
Maintainer: TheLastGimbus
Maintainer-email: mateusz.soszynski@tuta.io
Requires-Python: >=3.6,<4.0
Classifier: Development Status :: 2 - Pre-Alpha
Classifier: Intended Audience :: End Users/Desktop
Classifier: License :: OSI Approved :: Apache Software License
Classifier: Operating System :: POSIX :: Linux
Classifier: Programming Language :: C
Classifier: Programming Language :: Python :: 3
Classifier: Programming Language :: Python :: 3.10
Classifier: Programming Language :: Python :: 3.6
Classifier: Programming Language :: Python :: 3.7
Classifier: Programming Language :: Python :: 3.8
Classifier: Programming Language :: Python :: 3.9
Classifier: Topic :: Communications :: File Sharing
Requires-Dist: click (>=8.0.0,<9.0.0)
Requires-Dist: ifaddr (>=0.1.7,<0.2.0)
Requires-Dist: loguru (>=0.5.3,<0.6.0)
Requires-Dist: opendrop (>=0.13.0,<0.14.0)
Project-URL: Repository, https://github.com/TheLastGimbus/easydrop
